diyalgo/__init__.py
diyalgo/client/__init__.py
diyalgo/client/client.py
diyalgo/client/listener.py
diyalgo/expansions/__init__.py
diyalgo/features/__init__.py
diyalgo/features/feature.py
diyalgo/models/__init__.py
diyalgo/models/account.py
diyalgo/models/attachment.py
diyalgo/models/card.py
diyalgo/models/context.py
diyalgo/models/emojis.py
diyalgo/models/instance.py
diyalgo/models/poll.py
diyalgo/models/reaction.py
diyalgo/models/relationship.py
diyalgo/models/status.py
diyalgo/models/tag.py
diyalgo-0.1.0.dist-info/LICENSE
diyalgo-0.1.0.dist-info/WHEEL
diyalgo-0.1.0.dist-info/METADATA
diyalgo-0.1.0.dist-info/RECORD
