Metadata-Version: 2.1
Name: diyalgo
Version: 0.1.0
Summary: DIY Algorithms for Mastodon
License: AGPL-3.0
Author: sneakers-the-rat
Author-email: JLSaunders987@gmail.com
Requires-Python: >=3.9,<4.0
Classifier: License :: OSI Approved :: GNU Affero General Public License v3
Classifier: Programming Language :: Python :: 3
Classifier: Programming Language :: Python :: 3.9
Classifier: Programming Language :: Python :: 3.10
Classifier: Programming Language :: Python :: 3.11
Requires-Dist: Mastodon.py (>=1.8.0,<2.0.0)
Requires-Dist: beautifulsoup4 (>=4.11.1,<5.0.0)
Requires-Dist: lxml (>=4.9.2,<5.0.0)
Requires-Dist: pydantic (>=1.10.4,<2.0.0)
Requires-Dist: sqlmodel (>=0.0.8,<0.0.9)
